{
    "host": "default",
    "head": {
        "title": "Frontgate",
        "description": "Your Own Webpage Already Exists",
        "script": "js/default.js",
        "stylesheet": "css/default.css",
        "lang":"en",
        "favicon":"favicon.png"
    },
    "remote" : {
        "disabled": true,
        "script" : "http://hosts.medorc.org/frontgate/js/index.js",
        "_": [
            "The remote server where host site is stored"
        ]
    },
    "situs": {
        "disabled": false,
        "hostname": "situs",
        "protocol": "http:",
        "port": 80,
        "_": ["Server with Situs PHP Framework installed"]
    },
    "shebang": {
        "dir": "/htdocs/libs/jquery.bar/js/",
        "home": null,
        "_": [
            "dir: path or url to the json files a non secure http protocol url (not https)",
            "home: path or url to the Home json file (the Bar addon/hashbang config files)",
            ": remove or set falsy values to use the defaults"
        ]
    },
    "bars": {
        "header": {
            "_items":[{
            "text": "#!Home",
            "attr":{
                "title": "This is a shebang request.",
                "href": "?_escaped_fragment_=Home"
            }
        }]
        },
        "body": {
            "items":[{
                "text": "Bars",
                "attr": {
                    "class": "title",
                    "title": "Shebang Website for Frontgate Situs",
                    "style":"font-size: 50px"
                }
            },
            {
                "text": "PHP Shebang Boilerplate for JS Bar",
                "attr": {
                    "class": "subtitle"
                }
            }]
        },
        "footer": {
            "items":[{
                "html": "Copyright &copy; 2014",
                "attr": {
                    "href":"#copyright"
                }
            },
            {
                "text": "FRONTGATE",
                "attr": {
                    "href":"#frontgate"
                }
            },
            {
                "text": "frontgate.situs.pt",
                "attr": {
                    "href":"#situs"
                }
            },
            {
                "text": "info",
                "attr": {
                    "id":"contact",
                    "href": "#mailto"
                }
            }]
        },
        "notice": {
            "items":[{
                "el": "a",
                "text": "JavaScript is disabled"
            }]
        }
    },
    "data": {
        "ga":  "UA-XXXXXXXX-X",
        "_": {
            "ga": "Google Analytics ID"
        }
    }
}
